{"many": "\u00e6i", "freeze": "j\u00e6dud\u0251", "night": "\u00f8", "green": "vih\u0251nd", "sky": "t\u0251iv\u0251z", "year": "voz\u02b2", "leg": "j\u0251ug", "smell": "mujud\u0251", "because": "sik\u0283mi\u0283e", "hear": "kuld\u0251", "bark": "kor\u02b2", "stand": "sei\u0283t\u0251", "wife": "\u0251k", "stone": "kivi", "there": "sig\u00e6", "breast": "rind", "thick": "p\u0251ks", "yellow": "p\u0251kuine", "spit": "syl\u02b2k\u031ft\u0251", "swim": "ujud\u0251", "root": "jur\u02b2", "good": "hyv\u00e6", "in": "s", "child": "l\u0251ps\u02b2", "walk": "k\u00e6velt\u00e6", "road": "te", "seed": "semen", "guts": "soli\u0283t", "play": "v\u00e6t\u00e6", "mother": "m\u0251moi", "sew": "ombet\u0251", "some": "er\u0251z", "tree": "pu", "suck": "imed\u0251", "when": "konz", "cut": "t\u0283\u0251pt\u0251", "this": "netse", "old": "v\u0251nh", "husband": "mez\u02b2", "fog": "sumeg", "lie": "m\u0251g\u0251t\u0251", "hair": "ibus", "you": "ti", "bad": "hond", "fly": "let\u0251", "day": "p\u00e6iv", "blood": "t\u0283\u0251ki", "die": "kol\u0251", "hunt": "mets\u0251t\u0251", "kill": "rikt\u0251", "smoke": "s\u0251vu", "mountain": "m\u00e6gi", "warm": "l\u00e6m", "squeeze": "\u0251hti\u0283t\u0251d\u0251", "straight": "oiged", "big": "sur\u02b2", "leaf": "lehtez", "one": "yks\u02b2", "fingernail": "kynz\u02b2", "salt": "sol", "egg": "mun\u0251", "wet": "m\u00e6rg", "animal": "\u0292iv\u0251t", "head": "p\u00e6", "see": "n\u00e6ht\u0251", "horn": "s\u0251rv", "fear": "v\u0251r\u0251it\u0251", "burn": "p\u0251l\u0251d\u0251", "lake": "j\u00e6rv\u02b2", "moon": "ku", "split": "h\u0251ugoid\u0251", "if": "ku", "who": "ken", "ash": "tuhk", "breathe": "henkt\u00e6", "they": "hi", "know": "tet\u0251", "dry": "kuiv", "water": "vezi", "rotten": "l\u0251ho", "with": "yhtes", "knee": "komb", "skin": "n\u0251hk", "turn": "k\u00e6rout\u0251", "wind": "tulei", "other": "toine", "snow": "lumi", "cold": "k\u0251uged", "he": "h\u00e6n", "grass": "hein", "liver": "m\u0251ks\u0251", "fruit": "pilod", "correct": "oiged", "left": "hur\u0251", "tie": "sidod\u0251", "scratch": "kynst\u00e6", "woman": "n\u0251ine", "neck": "k\u0251gl", "not": "ei", "eye": "sil\u02b2m\u00e6", "small": "pen\u02b2", "river": "jogi", "all": "k\u0251ik", "star": "t\u00e6ht\u0251z", "thou": "sin\u00e6", "where": "kus", "flow": "jokst\u0251", "five": "vi\u0292", "narrow": "k\u0251id", "dog": "koir", "vomit": "okset\u0251", "heavy": "jyged", "name": "nimi", "sit": "i\u0283t\u0251", "wing": "sug", "far": "ed\u0251h\u0251n", "at": "l", "wash": "pest\u0251", "thin": "kyrz\u02b2", "sleep": "m\u0251g\u0251t\u0251", "we": "mi", "what": "mi", "float": "ujud\u0251", "cloud": "pilv\u02b2", "flower": "\u00e6nik", "two": "k\u0251ks", "three": "kume", "foot": "joug", "think": "melet\u0251d\u0251", "feather": "h\u00f8uneh", "and": "d\u0251", "fish": "k\u0251l\u0251", "nose": "nen\u0251", "sharp": "ter\u0251v", "come": "tuld\u0251", "pull": "ved\u0251d\u0251", "right": "oiged", "mouth": "su", "hold": "pid\u0251d\u0251", "sun": "p\u00e6iv\u00e6ine", "short": "lyhyd", "father": "t\u0251t", "laugh": "n\u0251grd\u0251", "near": "l\u00e6z", "here": "t\u00e6g\u00e6", "I": "min\u00e6", "sand": "lete", "say": "s\u0251nud\u0251", "wipe": "pyhkt\u00e6", "give": "\u0251nt\u0251", "four": "nel\u02b2\u00e6", "louse": "t\u00e6i", "full": "t\u00e6y\u0291", "tooth": "\u0251mb\u0251z", "forest": "mets", "dig": "k\u0251id\u0251", "that": "se", "few": "v\u00e6h\u00e6", "new": "uz\u02b2", "snake": "g\u0251d", "round": "kehker", "black": "must", "ice": "j\u00e6", "heart": "sy\u00e6in", "belly": "v\u0251ts", "sea": "meri", "wide": "leved", "dirty": "reduk\u0251z", "live": "el\u00e6d\u0251", "dust": "p\u00f8ly", "how": "kut", "eat": "s\u00f8d\u0251", "earth": "m\u0251", "bird": "lind", "man": "mez\u02b2", "rain": "vihm", "red": "rusked", "dull": "tylts", "white": "v\u0251uge\u028cd", "bone": "lu", "ear": "korv", "long": "pitk\u031f\u02b2", "tail": "h\u00e6nd", "throw": "t\u0251tst\u0251", "smooth": "t\u0251zo", "tongue": "kel\u02b2", "fire": "l\u00e6moi", "hand": "k\u00e6zi", "hit": "l\u00f8d\u0251", "blow": "puhud\u0251", "count": "l\u0251\u0283k\u0251", "drink": "jod\u0251", "sing": "l\u0251uld\u0251", "stab": "t\u0283ok\u0251it\u0251", "meat": "lih\u0251", "bite": "purd\u0251", "worm": "t\u0283undt\u0283", "fat": "r\u0251zv", "back": "selg", "rope": "nor", "fight": "tor\u0251t\u0251", "rub": "host\u00e6", "push": "tunkt\u0251", "human": "ristit", "stick": "k\u0251lu", "fall": "kirbot\u0251", "swell": "puhlot\u0251"}