{"right": "", "sun": "su\u027eija", "three": "", "swim": "ponim", "swell": "", "foot": "d\u0292e\u0288\u0288a", "sew": "", "tie": "", "smell": "", "throw": "", "back": "", "many": "pe\u027ee", "thick": "", "mouth": "muti", "ice": "", "wash": "", "dust": "", "small": "sinna", "short": "", "sit": "ud\u0259", "scratch": "", "dirty": "", "smooth": "", "head": "tal", "big": "b\u02b0umi", "rain": "\u028bana", "rope": "", "sea": "", "human": "", "egg": "sanku", "wide": "", "root": "\u028be\u027ekam", "river": "", "mountain": "dan\u0256ime\u0288", "split": "", "grass": "", "thou": "ninu", "give": "sitan", "child": "", "bird": "pi\u0288\u0288a", "meat": "mu\u027eija", "bone": "bokka", "flower": "", "smoke": "pog", "this": "id", "night": "si\u027ebedin", "old": "", "stick": "", "bark": "\u0256an\u0256ima\u0256\u0256a", "new": "kota", "two": "du\u0256\u0259", "rub": "", "dog": "ate", "fly": "tulsad", "sky": "", "tree": "mak", "straight": "", "knee": "mu\u0256su", "eye": "kan", "see": "tana", "snow": "", "fire": "kiss", "red": "jeru\u0256i", "fingernail": "", "seed": "\u028bittanam", "burn": "gon\u0256ka", "tail": "toka", "yellow": "pijuda", "bite": "ateka\u0282in", "one": "okkot", "fog": "", "woman": "baji", "hand": "keju", "all": "mak", "round": "bubba\u027ei", "and": "", "other": "", "push": "", "sharp": "", "leg": "", "flow": "", "dry": "ati\u027e", "bad": "", "live": "", "husband": "", "spit": "", "horn": "kommu", "not": "kadu", "at": "", "lie": "laba\u0256mu\u0256sati", "four": "", "father": "", "wet": "", "blow": "", "hear": "\u028binti", "wind": "", "five": "", "neck": "mak", "drink": "ani\u027eusat", "cold": "pani", "because": "", "few": "", "blood": "nettu\u027e", "green": "nigu\u027e", "thin": "", "skin": "tol", "liver": "kaleja", "turn": "", "leaf": "ak", "man": "mani\u0282an", "there": "", "tooth": "palku", "freeze": "", "hold": "", "heavy": "", "die": "tigten", "wipe": "", "say": "b\u02b0umi", "white": "tellu\u0256i", "feather": "bull", "correct": "", "he": "", "we": "amd\u0259", "fat": "b\u02b0umi", "warm": "\u028bekka", "count": "", "fish": "gu\u0256\u0256i", "good": "sobhatan", "vomit": "", "wing": "", "rotten": "", "where": "", "guts": "", "that": "ad", "forest": "", "kill": "alang\u0288an", "dig": "", "narrow": "", "they": "", "you": "", "louse": "panu", "play": "", "water": "i\u027e", "fight": "", "hunt": "", "left": "", "mother": "", "road": "daa\u027e", "suck": "", "breathe": "", "sing": "", "sand": "usuka", "cloud": "abar", "tongue": "nalka", "fruit": "", "if": "", "some": "", "hair": "ti\u027eu", "fear": "", "hit": "", "dull": "", "long": "po\u0256am", "name": "pe\u027e", "stab": "", "day": "", "near": "", "sleep": "imangsati", "come": "\u028ba", "year": "", "far": "", "squeeze": "", "here": "", "laugh": "", "fall": "", "heart": "gun\u0256e", "snake": "", "belly": "\u0288e\u0288\u0288e", "who": "b\u02b0umi", "star": "sukka", "salt": "", "black": "\u0256a\u027eiate", "eat": "antisatun", "moon": "nela", "earth": "b\u02b0umi", "in": "", "think": "", "lake": "", "with": "", "wife": "", "ash": "buggi", "animal": "", "ear": "ke\u028b", "full": "nin\u0256u", "when": "", "stand": "niman", "pull": "", "stone": "gun\u0256\u0259", "know": "u\u027etan\u0256at", "nose": "mukk", "float": "", "worm": "", "how": "", "cut": "", "I": "nenu", "breast": "satti", "what": "em", "walk": "na\u0256us"}