{"many": "", "flower": "blom", "bark": "", "skin": "", "wide": "", "heart": "h\u025bt", "cold": "", "some": "", "sea": "se", "father": "hait", "drink": "dr\u026a\u014bk\u0259", "yellow": "", "far": "", "tie": "", "this": "", "guts": "", "see": "", "ice": "is", "four": "", "sing": "", "forest": "", "pull": "", "thou": "", "stand": "ste\u0259n", "good": "", "there": "", "hair": "", "live": "l\u026abj\u0259", "float": "", "sharp": "", "if": "\u0254s", "I": "\u026ak", "sew": "", "know": "", "full": "", "tongue": "", "squeeze": "", "big": "", "fat": "", "stone": "sti\u0259n", "fruit": "", "hear": "j\u025br\u0259", "wash": "", "he": "h\u025bi", "with": "", "thin": "", "wing": "", "mouth": "mul\u0259", "short": "", "fingernail": "", "swim": "sv\u026amm\u0259", "rain": "rain", "dry": "", "spit": "", "lake": "", "seed": "", "stab": "", "long": "", "horn": "", "wife": "", "dirty": "", "hit": "", "here": "", "smell": "", "woman": "", "fog": "", "mother": "", "dog": "hun", "straight": "", "blood": "blu\u0259t", "tail": "", "sleep": "", "black": "", "salt": "", "sky": "", "warm": "varm", "wipe": "", "right": "", "new": "n\u025bi", "you": "do", "star": "", "left": "", "one": "", "eye": "\u026a\u0259x", "back": "r\u025bx", "die": "", "snake": "", "burn": "", "small": "", "animal": "", "dust": "", "push": "trjo\u0259", "not": "n\u025bt", "louse": "", "feather": "", "count": "", "tree": "b\u026a\u0259m", "fear": "", "snow": "sni\u0259", "play": "", "egg": "ai", "suck": "", "give": "jan", "root": "", "child": "b\u025bn", "fight": "", "hand": "", "five": "", "blow": "", "kill": "", "come": "", "three": "", "breathe": "", "head": "hol\u0259", "how": "", "split": "", "moon": "mwan\u0259", "neck": "", "vomit": "", "mountain": "b\u025brx", "name": "", "earth": "", "fish": "f\u026ask", "bite": "", "old": "\u0254t", "white": "vit", "human": "", "foot": "", "correct": "", "sand": "", "night": "naxt", "tooth": "", "sit": "", "flow": "", "rotten": "", "who": "", "what": "", "worm": "", "river": "", "wet": "", "husband": "", "laugh": "laitsj\u0259", "heavy": "swi\u0259r", "narrow": "", "grass": "\u0263\u025bs", "rub": "", "leaf": "", "all": "", "bird": "", "hunt": "", "because": "", "scratch": "", "cut": "", "fire": "fju\u0259r", "day": "", "dig": "", "smooth": "", "fall": "", "rope": "", "fly": "m\u026ax", "few": "", "sun": "", "they": "ja", "near": "", "bone": "", "in": "", "other": "", "that": "", "freeze": "", "and": "\u025bn", "two": "", "lie": "", "thick": "", "man": "minsk\u0259", "green": "\u0263ri\u0259n", "smoke": "", "wind": "", "road": "", "leg": "sko\u014bk", "walk": "", "belly": "", "where": "", "think": "", "liver": "", "knee": "", "we": "v\u025bi", "hold": "h\u0254d\u0259", "breast": "", "when": "", "swell": "", "water": "v\u025bt\u0259r", "dull": "", "stick": "", "bad": "", "cloud": "", "eat": "", "throw": "", "ash": "j\u026ask\u0259", "nose": "", "meat": "flais", "ear": "", "turn": "", "at": "", "year": "i\u0259r", "round": "", "say": "", "red": ""}