{"many": "\u0263i\u031e\u0279\u00e4t", "flower": "g\u0263u\u031e\u0279", "bark": "p\u00f8s\u031ep\u032a", "skin": "p\u0278\u0264\u027e\u030an\u030a", "wide": "l\u0251jn", "heart": "di\u031el", "cold": "sa\u027eg\u031f", "some": "", "sea": "b\u03b2\u025b\u0266\u0279", "father": "\u0294\u02b0\u0258d\u032a\u00e6\u027e", "drink": "\u0271\u0258\u0283\u031ew\u0264d\u028c\u0279", "yellow": "z\u025b\u027e", "far": "h\u025bru", "tie": "k\u0251p\u025bl", "this": "\u0294\u032cin", "guts": "p\u02b0o\u027eotik\u02b0", "see": "di\u031esd\u028c\u0279", "ice": "\u0270\u031f\u00e6s\u031e", "four": "t\u0283\u00e6h\u0252\u027e", "sing": "z\u0289\u031e\u027eut\u00e6\u0279", "forest": "gesar", "pull": "k\u0258\u0283id\u032a\u00e6\u0279", "thou": "to", "stand": "ist\u02b0\u0252d\u00e6\u0279", "good": "x\u031eu\u031eb\u032a", "there": "\u0252jndz\u00e4\u1d5d", "hair": "mo", "live": "\u0251p\u027e\u025bl", "float": "", "sharp": "t\u0258z", "if": "j\u00e6g\u00e6\u027e", "I": "\u03b2\u031e\u00e6n", "sew": "k\u0251\u027e\u025bl", "know": "d\u0251nesa\u0279", "full": "b\u0289\u0263\u031f", "tongue": "z\u028cb\u0254\u031en", "squeeze": "s\u025b\u0281m\u025bl", "big": "m\u025bts", "fat": "t\u0283arbi", "stone": "xa\u014b", "fruit": "m\u0268\u031ez\u031e\u025c\u0281", "hear": "\u0283\u0270d\u0268d\u028c\u0279", "wash": "s\u0289\u031es\u031ea\u0279", "he": "h\u0303o", "with": "p\u0254", "thin": "b\u0251\u027e\u0251k", "wing": "d\u0254\u028b", "mouth": "d\u00e6\u027e\u0252\u0271", "short": "k\u02b0u\u031ed\u02b1\u0252h", "fingernail": "\u0279\u0254xu\u031en", "swim": "l\u0254\u0281\u0251l", "rain": "b\u0279\u1d5dr\u0254\u0271", "dry": "\u0283\u031eosk", "spit": "t\u02b0\u0259k\u02b0\u025bl", "lake": "g\u0258\u027a\u0251", "seed": "t\u0289\u031ek\u0271", "stab": "\u03c7ots\u02b0\u025bl", "long": "d\u0268\u027e\u0258\u0292", "horn": "j\u0283\u0254k", "wife": "kin", "dirty": "k\u031f\u00e6\u03c7s\u0268", "hit": "z\u031e\u0250b\u00e6\u0279", "here": "\u0268\u0279dz\u00e4\u1d5d", "smell": "h\u0254t", "woman": "kin", "fog": "mah", "mother": "m\u0252d\u00e6r", "dog": "s\u028c\u031eg", "straight": "most\u00e6\u0263im", "blood": "kun", "tail": "d\u0268m\u030a", "sleep": "\u0254\u031eg\u0268d\u00e6\u0279", "black": "si\u031e\u029d\u0252h", "salt": "nam\u00e6k", "sky": "j\u00e4\u1d5ds\u014b\u0251n", "warm": "g\u0263\u031f\u00e6\u027em", "wipe": "s\u0259\u027ep\u02b0\u025bl", "right": "i\u027e\u0251vu\u014bk\u02b0", "new": "nu\u031e", "you": "t\u0289\u031e", "star": "\u0268t\u00e4\u1d5dz\u031e\u00e6", "left": "t\u0283ap", "one": "\u0272e\u031ek\u031f", "eye": "t\u0283at\u0283b", "back": "p\u0289\u031et\u0283t", "die": "m\u0289\u031erd\u00e6\u0279", "snake": "m\u0254\u031er\u030a", "burn": "z\u0289kp\u032a\u00e6\u0279", "small": "k\u02b0u\u031et\u0283\u02b0\u0250k", "animal": "d\u00e4\u1d5dnz\u031ea\u027e", "dust": "p\u02b0o\u0283i", "push": "h\u0259\u027e\u025bl", "not": "n\u030a\u00e6", "louse": "\u0283\u031e\u0258p\u0278es", "feather": "p\u025b\u0254\u031er", "count": "\u0283u\u031emu\u031erd\u00e6n", "tree": "d\u0258\u027ext\u02b0", "fear": "v\u0251\u03c7", "snow": "dzjun", "play": "\u03c7\u0251\u0281\u0251l", "egg": "tu\u031exm", "suck": "m\u00e6k\u0268\u031ede\u031e\u0279", "give": "d\u0252d\u00e6\u0279", "root": "r\u0259s\u031e", "child": "d\u028cdzeq", "fight": "k\u0259rv\u025bl", "hand": "d\u00e6st", "five": "\u0294\u02b0\u025bnd\u0292", "blow": "p\u02b0\u0259t\u0283\u02b0\u025bl", "kill": "ko\u0283t\u00e6\u0279", "come": "\u03b2ad\u028c\u0279", "three": "j\u025b\u027e\u025bk\u02b0", "breathe": "\u0283\u0259nt\u0283\u02b0\u025bl", "head": "x\u0250r", "how": "int\u0283\u02b0p\u025bs", "split": "", "moon": "lusin", "neck": "g\u025brd\u00e6n", "vomit": "", "mountain": "g\u0263\u0268\u0266", "name": "n\u0254\u031e\u0271", "earth": "h\u0254\u0281", "fish": "m\u0254\u031exi", "bite": "g\u0250zid\u00e6\u0279", "old": "\u0294\u032c\u025bb\u032am", "white": "se\u0278\u0268", "human": "m\u0251\u027et\u02b0k\u0251jin", "foot": "p\u032a\u025btk\u02b0", "correct": "d\u0275\u027eost", "sand": "r\u0258g", "night": "\u0283\u00e6d", "tooth": "dand\u0252n", "sit": "ne\u00e6st\u02b0\u00e6\u0279", "flow": "hos\u025bl", "rotten": "p\u02b0\u0259t\u0251ts", "who": "k\u02b0\u0258\u029d", "what": "nt\u0283\u02b0e", "worm": "g\u0268rn", "river": "xen", "wet": "s\u031e\u0268ts", "husband": "\u0283o\u031e\u0268\u02b7h\u025b\u027e", "laugh": "x\u025bndi\u031e\u0279", "heavy": "sa\u014b\u0268n", "narrow": "n\u025b\u0281", "grass": "s\u031e\u025bbz", "rub": "m\u0252lid\u032a\u00e6n", "leaf": "b\u00e6\u027eg", "all": "\u0278\u025b\u03b2\u031e\u0258", "bird": "p\u00e4\u027ea\u02b1n\u1d5dd\u025b", "hunt": "v\u0254\u027es\u0251l", "because": "v\u0254\u027e\u0254fh\u025bt\u025bv", "scratch": "x\u00e6\u027e\u0252id\u00e6\u0279", "cut": "bo\u031e\u027eid\u00e6\u0279", "fire": "k\u0259\u027e\u0251k", "day": "roz", "dig": "k\u025bd\u00e6\u0279", "smooth": "h\u0251\u027et\u02b0", "fall": "o\u031evk\u02b0d\u028c\u0279", "rope": "ar\u0281amin", "fly": "m\u030a\u025c\u0279s", "few": "k\u025bm\u030a", "sun": "\u0254\u031eft\u025eb\u032a", "they": "h\u0303es\u0252n", "near": "n\u025bzdk\u031f", "bone": "vostu\u031ex\u0254\u031en", "in": "d\u00e6r\u030a", "other": "gig\u02b2\u00e6\u027e", "that": "\u0252n", "freeze": "", "and": "\u0289\u031e", "two": "du", "lie": "do\u027e\u0263", "thick": "h\u0251st", "man": "m\u026f\u031e\u027eoz\u031e", "green": "sab\u0251\u0292", "smoke": "tsu\u03c7", "wind": "g\u0252d", "road": "t\u0283\u0251n\u0251p\u0251\u027e", "leg": "p\u032a\u0252", "walk": "ga\u00e7d\u00e6\u0279", "belly": "\u0283i\u031ek\u025bm", "where": "g\u02b1odzt\u00e4\u1d5d", "think": "\u0278\u0264k\u027ek\u02b2\u028c\u027ede\u031e\u0279", "liver": "dzi\u031egar", "knee": "z\u0254n\u026f", "we": "m\u0254", "hold": "b\u0259rn\u025bl", "breast": "p\u02b0\u0258st\u02b0\u0252d", "when": "g\u02b1ej", "swell": "ur\u025bl", "water": "\u0254b", "dull": "but\u02b0", "stick": "tob", "bad": "b\u032aad", "cloud": "\u0294ab\u2c71\u031f", "eat": "xw\u027e\u0268\u0279", "throw": "\u00e6nd\u0254xt\u00e6\u0279", "ash": "wk\u02b2e\u026ct\u032a\u02b0e\u027e", "nose": "gidi", "meat": "g\u00f8\u0283t", "ear": "go\u0283", "turn": "d\u0250st\u00e6\u0279", "at": "d\u00e6\u027e", "year": "s\u0252l", "round": "g\u0259rd", "say": "goft\u00e6\u0279", "red": "\u0262\u0258\u027emez"}