{"many": "\u0272iaw", "flower": "twka", "bark": "p\u0271\u026f\u031eag", "skin": "na\u014b", "wide": "k\u03b2\u031e\u00e4\u0270\u0270\u031f\u03b2\u031e\u00e7\u031e", "heart": "\u0255\u031ee\u031e\u0272", "cold": "\u0279e\u031ejn", "some": "b\u0251\u0294\u014b\u031f", "sea": "\u0294\u02b0\u03b2\u031e\u0279\u0268\u031e", "father": "\u0294b\u02b1\u025e", "drink": "d\u026fm", "yellow": "\u028b\u026fa\u014b", "far": "z\u02e1aj", "tie": "\u00e7\u031eog", "this": "ni", "guts": "", "see": "\u00e7en", "ice": "n\u030aabk\u02b0\u025b\u014b", "four": "t\u0258i", "sing": "\u0294\u02b0apr\u0254\u014b", "forest": "d\u0250\u014b", "pull": "d\u0268\u0270", "thou": "p\u02b0\u026f\u0279", "stand": "\u0279\u026fn", "good": "d\u0268t", "there": "nan", "hair": "t\u02b0\u0264mp", "live": "i\u0255\u02b0\u0268w\u0268n\u030a", "float": "noj", "sharp": "t\u02b0\u0264\u014b", "if": "n\u030a\u02b0\u00e6w", "I": "t\u02b0o\u031e\u03b2\u031e", "sew": "\u0270eb", "know": "\u0299u", "full": "\u0294\u0257\u0259j", "tongue": "lin\u02c0", "squeeze": "di\u031e", "big": "", "fat": "k\u02b0ajm\u00e4n", "stone": "h\u0279\u0272", "fruit": "\u03b2\u031ei\u031e", "hear": "dajjin", "wash": "z\u02e1\u0250\u014b\u031f", "he": "\u0294\u02b0\u00e6j", "with": "g\u00e4b", "thin": "ba\u014bm", "wing": "p\u032aik\u031f", "mouth": "pi\u00e4k", "short": "xan", "fingernail": "n\u02e1e\u031ebm\u03b2\u031e", "swim": "\u03b2\u031e\u00e4jnam", "rain": "\u0278u\u014b\u031f", "dry": "xe\u014b", "spit": "\u0272o", "lake": "s\u031e\u0254k", "seed": "ma\u0279\u030a\u02e1\u0258t\u0294\u02b0an", "stab": "d\u02b1\u025b\u014b", "long": "\u029da\u03b2\u031e", "horn": "t\u02b0\u0250\u0270\u1d5d", "wife": "ar\u0268\u00e7\u031ea", "dirty": "okp\u00e4rok", "hit": "\u0294d\u0268", "here": "t\u02b0ini", "smell": "n\u02e1\u0268\u0279", "woman": "p\u032a\u02b0u\u0294\u0272\u0268", "fog": "mo\u031ek", "mother": "m\u00e6", "dog": "m\u030a\u00e4", "straight": "tro\u014b", "blood": "l\u03b2\u031eap", "tail": "h\u0257\u00e4\u014b\u031f", "sleep": "no\u031e", "black": "dam", "salt": "\u014b\u030a\u026f\u00e4", "sky": "t\u0250", "warm": "\u0294\u0289n", "wipe": "t\u0255\u02e1\u02b0e\u031ep", "right": "xwi\u031e\u0259d\u0279\u02b1\u0268\u0294", "new": "m\u025e\u031ej", "you": "h\u0303i\u031e\u014b", "star": "ta\u0270\u1d5d\u0257", "left": "tsaj", "one": "m\u026fg", "eye": "n\u030aa", "back": "l\u0250\u014b", "die": "ts\u00e6\u00e7\u031e", "snake": "n\u026f", "burn": "m\u030aaj", "small": "n\u02e1\u0258k", "animal": "sv\u00e4t", "dust": "vu\u0279", "push": "t\u0251n", "not": "g\u0258w\u0270m", "louse": "h\u00e4m\u02e0", "feather": "kx\u02e1\u02b0o\u031ennu\u031e", "count": "d\u00e6p", "tree": "p\u032am\u00e4j", "fear": "klua", "snow": "s\u031em\u00e4c", "play": "\u028ee\u0279", "egg": "c\u00e7\u02b0\u0250\u0270\u031f", "suck": "but", "give": "h\u025cg", "root": "r\u030a\u00e6k", "child": "\u0279\u0289p", "fight": "tsinz\u0259u", "hand": "b\u0268", "five": "s\u031eam", "blow": "p\u02b0\u0251d", "kill": "t\u02b0i\u00e4", "come": "da", "three": "\u0294tam", "breathe": "hac\u031f\u00e4j", "head": "h\u0279\u025e\u031e", "how": "ja\u014b\u014baj", "split": "t\u0255\u025b", "moon": "o\u014b\u025f\u031f\u028c\u031en", "neck": "ko\u031e", "vomit": "t\u0255i\u0251n", "mountain": "p\u02b2\u026f", "name": "c\u031f\u0268", "earth": "d\u0268n", "fish": "pla", "bite": "kat", "old": "ka\u0270\u1d5d", "white": "ca\u0270\u1d5d", "human": "", "foot": "\u0294t\u025bm\u0259", "correct": "ki\u031ewk", "sand": "xa", "night": "\u0294\u0279\u00e6n", "tooth": "t\u025b\u014b", "sit": "n\u0251\u014b\u031f", "flow": "\u028eaj", "rotten": "n\u00e4wp\u0294", "who": "\u0294\u02b0raj", "what": "r\u00e6\u0270", "worm": "no\u031en", "river": "\u025b\u0279\u030a\u0251m", "wet": "pi\u00e4k", "husband": "tso\u031e\u0264\u031e", "laugh": "k\u02b0\u00e4\u03b2\u031e", "heavy": "nak", "narrow": "\u0294\u02b0\u025bp", "grass": "\u00e7\u031e\u028c", "rub": "k\u02b0at", "leaf": "da\u0270", "all": "", "bird": "\u014b\u030a\u0275\u014b\u030a", "hunt": "san\u0294\u0253an", "because": "t\u02b0\u029d\u028c\u0294v", "scratch": "ga\u03b2\u031e\u02e0\u02c0", "cut": "tat", "fire": "v\u0250\u0270\u031f", "day": "m\u0276\u0279", "dig": "\u0294k\u026fp", "smooth": "viak", "fall": "k\u00f8k", "rope": "d\u0291\u02b1\u0268ak", "fly": "az\u02e1\u025b\u014bw\u00e4\u0279", "few": "n\u030a\u028c\u00e7\u031e", "sun": "daba\u030a\u0258\u025f", "they": "\u0294\u02b0\u00e4\u028d", "near": "\u026e\u00e4\u0272", "bone": "kr\u0250d\u0289k", "in": "n\u030aa\u0270", "other": "ki\u014b", "that": "d\u00e4", "freeze": "k\u025b\u014b\u0253", "and": "\u0279\u00e6\u0294\u032c\u1d5d", "two": "x\u025c\u0272", "lie": "n\u0254jzoj", "thick": "na", "man": "mn\u0289\u025f", "green": "k\u02b0\u0272aw", "smoke": "k\u02b0w\u00e4\u0279", "wind": "lom", "road": "\u0294\u0279\u0279o\u031en", "leg": "kx\u031f\u02b0\u00e4", "walk": "de", "belly": "t\u025ew\u014bm\u0294", "where": "\u0294\u02b0id\u00e4\u0270\u031f", "think": "\u014b\u030a\u02b0it", "liver": "kam\u030a", "knee": "k\u00e4w\u0263", "we": "t\u02b0\u0263\u1d5d\u0251k\u0251\u0270\u031f\u1d5d", "hold": "d\u02b1\u0268", "breast": "p\u032au\u031e", "when": "\u014b\u026fa", "swell": "d\u0289am", "water": "\u014b\u00e4\u014b", "dull": "kun", "stick": "g\u0289\u0279", "bad": "z\u02e1ew", "cloud": "m\u030a\u0258g", "eat": "ki\u031enk\u02b0\u00e4\u014b\u1d5d", "throw": "\u0272\u0275n", "ash": "ts\u02b0\u00e4", "nose": "tsam\u026fg", "meat": "d\u026f\u0279", "ear": "s\u031ea\u0289", "turn": "mun", "at": "t\u02b0i", "year": "m\u030ai\u031e", "round": "sw\u025b", "say": "m\u02e0\u00e4w", "red": "d\u025c\u014b"}