{"all": "\u03c7\u031e\u00e4\u0270\u025b", "mother": "y\u025f\u02b1\u0264\u014b\u030a", "correct": "p\u0259dar\u030a", "forest": "\u0268t\u026cat\u02b0\u0272", "throw": "\u0294\u032c\u028ck\u02b0\u025cn\u025cl", "wash": "maghugas", "fire": "ne\u03b2\u03c7j\u00e4", "pull": "tare\u0294", "tie": "d\u025bb\u02bc\u0272r\u03b2\u031e", "near": "d\u0259kat", "yellow": "b\u0153\u031e\u0279tep\u0275", "nose": "ydz\u031e\u0264\u031e", "two": "tw\u0273e\u0288t\u026f", "eat": "\u0272tz\u031eia", "good": "\u0259p\u0278le\u0288j", "fat": "b\u0258\u028b\u0252t\u02b0i\u031e", "think": "k\u031f\u00e6\u014bi\u031ezh", "turn": "\u0263t\u00e6pe", "cold": "t\u00e6\u03b2\u031e\u014b\u02e1t", "name": "m\u025bn", "push": "tor\u02e1\u0252\u0294\u032c", "earth": "d\u02b1\u026c\u00e4pde\u031e", "dig": "gali", "liver": "\u0294\u00e6di\u031en\u02b1u", "stab": "\u0279is\u02bcw\u025cp\u0259", "scratch": "\u03c7\u025b\u0278\u00e4n\u02bckx\u02bc\u0270\u00e4", "live": "e\u030a\u00e6\u0279li\u031et", "know": "ce\u031e\u0279n\u030a\u0294\u0264\u0256\u1d5d", "tail": "\u00e6t\u026c\u028c\u031eni", "worm": "isi\u0253ungu", "who": "\u0279p\u0270\u031f", "burn": "g\u00e6\u027e\u00f8\u0256", "human": "\u00e4p\u02bc\u025c\u030a\u1d5dd\u0292\u02e0\u00e4j", "hear": "t\u0268\u031e\u0273e", "dry": "\u00e6ti\u031ena", "fish": "i\u014b\u0272", "rub": "\u0279\u1d5d\u0283\u031e\u02b0\u0268\u031ez\u031eq\u03c7\u0275\u031en\u02e1\u0268", "with": "d\u0259\u014ban", "old": "l\u0252ma", "and": "\u0279a", "animal": "\u03b2\u031esim\u02e0an\u030ae\u031e", "big": "p\u0258\u026d\u0273\u025c\u0279", "smooth": "drk\u00e4r\u02e1\u025c", "horn": "x\u031e\u0264ni\u025f", "knee": "\u0279u\u031ek\u0258", "stick": "\u03b2\u031e\u0272d\u0268\u014b\u2193u", "foot": "a\u014b\u025bp\u0279\u1d5dd\u0292", "spit": "ludah", "guts": "nt\u0283\u02bc\u00e6\u0270", "tongue": "\u0279\u030aa\u0279\u00e6p\u032a", "salt": "tswajti", "few": "p\u0278\u02bc\u026f\u031ek\u02bc\u02b0\u025b", "leaf": "t\u02b0\u00e6\u0294h\u0258", "wing": "\u0268k\u02b0ig\u031f\u2193\u0275", "rope": "ntan\u0264", "flower": "m\u030a\u02bcimb\u00e4\u1d5d\u029f\u0268", "wipe": "\u0279\u030a\u02bcimtsend\u00e6", "smoke": "\u026f\u031et\u025b", "blow": "d\u00e6\u0299\u025eba", "day": "\u0268\u030a\u1d5dz\u0268\u0257y", "year": "\u0279\u1d5dahg\u0279", "play": "magla\u027eo\u0294", "you": "we\u031en\u03b2\u031e", "many": "de\u031e\u014b\u030a\u031f\u029dg\u025c", "louse": "p\u03b2\u031e\u028cni", "if": "jlu\u031es", "in": "sa", "this": "idu", "that": "\u025bc", "other": "i\u0283kva", "long": "d\u0258\u0279\u0256av", "fog": "ink\u0268ngu\u031e", "here": "sini", "hunt": "\u00e6t\u0279\u0320\u0281\u1d5d\u03b2\u031e\u00e4", "sea": "lwa\u014b\u026ce", "sky": "la\u014bi\u031et", "at": "di", "far": "d\u0292aoh", "bad": "buru\u0294", "snake": "\u026fje\u0257a", "one": "\u0264n\u030a\u025f", "root": "e\u03b2pe\u031e\u027e\u0259", "mountain": "\u014b\u0264d\u0259\u0273", "give": "ge\u031e\u027dr\u030a\u025b", "egg": "\u0272\u01c3e\u031ed\u0288\u0282\u031e\u02e1\u026f", "five": "z\u031ein\u030a\u00e6", "short": "p\u02bcu\u031et\u02bc\u0279a", "because": "t\u0268s\u031e\u0268g\u1d5d", "tooth": "d\u025bg\u029f\u031d\u0289", "fall": "d\u025b\u0279\u0259p\u02b0", "dog": "\u014be\u0272t\u025b\u014b", "sun": "\u03b2\u0268c\u0268\u031ea", "skin": "te\u0279k\u031f", "sew": "t\u026c\u02bce\u0299\u00e6", "some": "n\u00e4ni", "father": "\u0253ap\u0278\u2193\u00e6", "fear": "takut", "fruit": "\u03b2\u031es\u0268e\u031e\u0279\u030a\u02e1o", "man": "\u0264\u027drj\u0288\u028c", "narrow": "n\u0263\u031f\u0279\u0279\u030a\u02bcru", "dirty": "kotor", "hand": "s\u031ee\u031e\u014b\u02b1i", "what": "\u025b\u0273n\u030ag", "fight": "awajin", "warm": "\u0278eg\u0263k\u00e6t", "grass": "\u0289tsan\u026f", "lie": "abs\u025bmu\u031ekxni\u031e", "bone": "pu\u031ek\u025f\u0279\u0153", "where": "diman\u0259", "smell": "bau", "swell": "\u0292\u014bp\u00e6\u0299a", "neck": "\u0279\u0288j\u0266\u0303\u025f\u0279\u1d5d", "red": "nr\u030a\u0268\u031e\u0256eh", "stone": "\u025f\u00e4\u1d5dn\u030a\u0264\u031e", "bark": "\u0279g\u031fd\u0256\u1d5d\u025e\u031e", "hold": "\u025ckx\u02bc\u02b0\u0279\u025bde\u031e", "road": "b\u032avad\u0270\u031f\u1d5d\u0272", "sleep": "\u0259s\u028c\u031ez\u031e\u1d5d\u0263\u028c", "how": "\u0260a\u0272d\u0292ani", "flow": "alor", "full": "d\u0268\u031en\u0256e", "see": "ke\u031ete\u031e", "seed": "\u026f\u0270\u031f\u0273e\u031e\u0266\u0303\u02e0", "when": "pe\u031e\u03b2\u031e\u025b", "sand": "\u025f\u029d\u0270\u031ft\u025b", "float": "t\u025bp\u032at\u02b0\u026fvi", "straight": "p\u02b0\u0268\u031e\u0279in", "green": "\u0294m\u025bd\u0292\u031e\u02e1\u025f\u029dg\u031f\u1d5d", "cut": "\u0279\u1d5dt\u0283\u02bck\u02bci\u0263\u026f\u030a\u1d5da", "black": "h\u0303\u0250\u0278\u031e\u02b0\u0288e", "snow": "\u0268t\u02b0\u02bc\u2193wa", "ear": "t\u02b0e\u031e\u0279i\u031e\u014b", "wet": "basah", "lake": "i\u01c3ent\u2193i\u031e", "sharp": "kx\u02bcg\u025cnt\u02b0\u026f\u0279e", "white": "\u03b2\u0264\u0279\u030a\u0278\u031e\u0258", "husband": "n\u0270en\u0272i", "stand": "z\u031ei\u03b2\u031ete\u031eno", "round": "bu\u0273be\u031edi\u031e", "hair": "\u0263g\u0263\u0272\u03b2\u031e\u0258", "say": "i\u031e\u025f\u03b2\u031e\u026f", "laugh": "tajpm\u02e0\u00e4ht", "they": "m\u2193o\u031enk\u00e6d\u02b1", "tree": "b\u028ct\u0258\u0294", "not": "bed\u026ee", "mouth": "n\u0275\u031ej\u0270", "left": "kiri", "freeze": "d\u00e6kjn\u0268m\u00e6", "bird": "pz\u031e\u0264\u0288te\u014b", "thou": "ne\u0271m", "count": "\u0279\u0264ht\u00e4ht", "woman": "p\u0272s\u031ee\u031e\u0279\u0268", "star": "\u025f\u03b2\u031e\u014bt\u00e6", "water": "t\u014b\u0294\u0279\u0263", "wind": "\u0268m\u026f\u031e\u014b\u031f", "swim": "\u0266\u0303u\u0264d\u0256\u0268\u031eht", "wide": "malapad", "ice": "e\u01c3m\u02e0\u00e6", "blood": "n\u00e6de\u031en\u030a", "split": "du\u0279da", "four": "\u0272e\u031eaj\u028ee", "come": "t\u0270n\u030a\u00e4g\u0263", "heavy": "b\u0259rat", "right": "xa\u0294a", "thin": "d\u02b1\u03c7\u0268\u031et\u03c7\u0268", "new": "\u03b2\u031e\u025fd\u00e4\u1d5d", "sing": "lavluht", "breast": "\u0272\u0253i\u031enti", "head": "t\u00e4\u0272\u029f\u0270\u031f\u00e6", "walk": "z\u031e\u00e6\u0288\u0268\u031e\u0279", "there": "toppe", "moon": "d\u028c\u0279g\u031fdz\u031e", "small": "t\u0268\u031en\u030a\u0279\u0279", "belly": "\u0288\u0289\u031e\u0256ok\u031f", "he": "\u0279i\u031ena", "drink": "\u014b\u031f\u0268\u014b\u0258", "hit": "\u0279\u03c7\u031eb\u0259r", "sit": "ud\u0268t\u0264", "we": "g\u00e6\u03b2\u031em\u0259", "suck": "hisap", "heart": "dzin\u00e7\u031ej\u1d5d\u028c\u031e", "rain": "n\u1d5d\u0279\u0320\u00e6m", "night": "\u025e\u031ed\u025f\u03b2\u031e", "dull": "d\u00e4\u1d5dgu\u0279\u00e6", "three": "k\u0275pn\u00e4", "eye": "\u014bj\u0279\u030a\u014b\u031f", "leg": "u\u031ex\u031f\u02e1e\u0263\u0258", "feather": "gpe\u031e\u0273\u02b1j", "river": "\u0289\u026f\u028e\u031d\u025b", "thick": "s\u02bc\u0263l\u026f", "rotten": "\u0274\u0153r\u030a\u03b2\u031eg\u0258\u02e0r\u02e1i\u031e", "I": "\u014be\u0279\u0268\u031e", "fingernail": "\u026f\u030a\u1d5d\u0268k\u02b0u\u031e", "cloud": "\u00e6ban\u030a\u0279", "vomit": "muntah", "breathe": "b\u0259rnafas", "squeeze": "\u03b2\u031e\u028cntsj\u0299\u0259", "dust": "h\u0268p\u02b0u\u028bi\u030a", "meat": "b\u00e6\u014b\u025b\u014b\u030a\u031f\u026f\u031e", "bite": "d\u0258\u014be", "back": "\u03b2\u031e\u014b\u031f\u0279\u030a\u02e1a\u014be\u031e", "child": "\u014bta\u0279\u0320na", "kill": "\u014b\u030a\u0251nbun\u0275h", "wife": "istri", "fly": "\u0279\u014b\u0279\u025fts\u02b0", "ash": "bu\u031en\u025f", "die": "p\u00e6den"}